diacritization_evaluation/__init__.py
diacritization_evaluation/constants.py
diacritization_evaluation/der.py
diacritization_evaluation/util.py
diacritization_evaluation/wer.py
diacritization_evaluation-0.5.dist-info/LICENSE.txt
diacritization_evaluation-0.5.dist-info/METADATA
diacritization_evaluation-0.5.dist-info/WHEEL
diacritization_evaluation-0.5.dist-info/top_level.txt
diacritization_evaluation-0.5.dist-info/RECORD
