Metadata-Version: 2.1
Name: diacritization-evaluation
Version: 0.5
Summary: This package calculates Diacritization Error Rate (DER) and Word Error Rate (WER)
Home-page: https://github.com/almodhfer/diacritization_evaluation
Author: Mokhtar Madhfar
Author-email: mokhtarmodhfer@gmail.com
License: MIT
Download-URL: https://github.com/almodhfer/diacritization_evaluation/archive
Keywords: diacritization,WER,DER
Platform: UNKNOWN
Classifier: Development Status :: 5 - Production/Stable
Classifier: Intended Audience :: Developers
Classifier: Topic :: Software Development :: Build Tools
Classifier: License :: OSI Approved :: MIT License
Classifier: Programming Language :: Python :: 3
Classifier: Programming Language :: Python :: 3.4
Classifier: Programming Language :: Python :: 3.5
Classifier: Programming Language :: Python :: 3.6
Classifier: Programming Language :: Python :: 3.7
Classifier: Programming Language :: Python :: 3.8
